[
  {
    "id": 28058171062,
    "product_name": "Ginno Cat Gourmet กินโนะ อาหารเปียกแมว เกรดพรีเมียม 60g. ไม่เติมเกลือ มีโอเมก้า 3",
    "tags": [
      "อาหารแมว",
      "อาหารแมว-เกรดพรีเมียม"
    ],
    "order": 23800,
    "price": 16,
    "url_img": "https://down-ws-th.img.susercontent.com/th-11134207-7r98w-lz22gjvtqao1d5.webp",
    "url_shopee": "https://s.shopee.co.th/9zlurWfz6o",
    "location": "โกลเด้นบั๊ก",
    "sale_date": "5",
    "expiry_date": "0.80",
    "supplier": "https://shopee.co.th/product/47780077/28058171062"
  },
  {
    "id": 26314768869,
    "product_name": "Pramy Supreme พรามี่ ซูพรีม อาหารแมวเม็ด เกรดพรีเมียม ขนาด 800g-1kg",
    "tags": [
      "อาหารแมว",
      "อาหารแมว-เกรดพรีเมียม"
    ],
    "order": 5000,
    "price": 99,
    "url_img": "https://down-ws-th.img.susercontent.com/th-11134207-7rask-m1mrwabzy5wp19.webp",
    "url_shopee": "https://s.shopee.co.th/AA5L3pfLlr",
    "location": "PG.Pets",
    "sale_date": "7",
    "expiry_date": "6.93",
    "supplier": "https://shopee.co.th/product/228830584/26314768869"
  },
  {
    "id": 22087460801,
    "product_name": "Bite Of Wild 50g อาหารแมวเกรดพรีเมี่ยมสําหรับแมวทั้งหมดอายุไม่เกิน 92% เนื้อเนื้อหา 42%",
    "tags": [
      "อาหารแมว",
      "อาหารแมว-เกรดพรีเมียม"
    ],
    "order": 14100,
    "price": 27,
    "url_img": "https://down-ws-th.img.susercontent.com/cn-11134207-7ras8-mauqlab757sp40.webp",
    "url_shopee": "https://s.shopee.co.th/9f94SuhFmm",
    "location": "Bite of Wild Official Shop",
    "sale_date": "8",
    "expiry_date": "2.16",
    "supplier": "https://shopee.co.th/product/990764810/22087460801"
  },
  {
    "id": 15890909614,
    "product_name": "(1ซอง)Pramy Carnivore อาหารเปียกแมว พรามี่ คาร์นิวอร์ เกรดพรีเมี่ยม ขนาด 70g. แบบ 1ซอง",
    "tags": [
      "อาหารแมว",
      "อาหารแมว-เกรดพรีเมียม"
    ],
    "order": 19600,
    "price": 15,
    "url_img": "https://down-ws-th.img.susercontent.com/th-11134207-7r98x-lvmu42pkbn0c7e.webp",
    "url_shopee": "https://s.shopee.co.th/9pSUfDgcRp",
    "location": "PET VELAA",
    "sale_date": "4",
    "expiry_date": "0.60",
    "supplier": "https://shopee.co.th/product/831512945/15890909614"
  },
  {
    "id": 24782593166,
    "product_name": "[ ตกกิโลละ 119 บาท l ไซส์กระสอบ 15 กิโล ] petheria อาหารแมวแบบเม็ดเกรด SUPER PREMIUM มีให้เลือกทุกช่วงวัย",
    "tags": [
      "อาหารแมว",
      "อาหารแมว-เกรดพรีเมียม"
    ],
    "order": 3900,
    "price": 1800,
    "url_img": "https://down-ws-th.img.susercontent.com/th-11134207-7r98s-lwvhzisxlp73e0.webp",
    "url_shopee": "https://s.shopee.co.th/9KWE4IiWSk",
    "location": "petheriaFamily",
    "sale_date": "7",
    "expiry_date": "125.86",
    "supplier": "https://shopee.co.th/product/306728272/24782593166"
  },
  {
    "id": 29505427979,
    "product_name": "Buzz Beyond บัซซ์ บียอนด์ อาหารแมวเกรดพรีเมียม กลูเตนฟรี (ถุงแบ่งโรงงาน) 1kg",
    "tags": [
      "อาหารแมว",
      "อาหารแมว-เกรดพรีเมียม"
    ],
    "order": 1800,
    "price": 105,
    "url_img": "https://down-ws-th.img.susercontent.com/th-11134207-7r98u-lyqg0w5k0be14a.webp",
    "url_shopee": "https://s.shopee.co.th/9UpeGbht7n",
    "location": "Petto Land",
    "sale_date": "7",
    "expiry_date": "7.35",
    "supplier": "https://shopee.co.th/product/76612376/29505427979"
  },
  {
    "id": 25783257067,
    "product_name": "YTL อาหารแมวเกรดพรีเมี่ยม อาหารแมวเปียก อาหารแมวกระป๋อง อาหารสุนัข 85g.วันที่ผลิตสด พร้อมส่ง",
    "tags": [
      "อาหารแมว",
      "อาหารแมว-เกรดพรีเมียม"
    ],
    "order": 4000,
    "price": 9,
    "url_img": "https://down-ws-th.img.susercontent.com/sg-11134201-7rdyv-lxhzcyhdjex461.webp",
    "url_shopee": "https://s.shopee.co.th/8ztNfgjn8i",
    "location": "bobolove",
    "sale_date": "7",
    "expiry_date": "0.63",
    "supplier": "https://shopee.co.th/product/378319270/25783257067"
  },
  {
    "id": 29522973196,
    "product_name": "Ginno Cat Gourmet กินโนะ อาหารเปียกแมว เกรดพรีเมียม 60g.x12 ไม่เติมเกลือ มีโอเมก้า 3",
    "tags": [
      "อาหารแมว",
      "อาหารแมว-เกรดพรีเมียม"
    ],
    "order": 2500,
    "price": 189,
    "url_img": "https://down-ws-th.img.susercontent.com/th-11134207-7ras8-m4rdan2ayemid0.webp",
    "url_shopee": "https://s.shopee.co.th/9ACnrzj9nl",
    "location": "โกลเด้นบั๊ก",
    "sale_date": "5",
    "expiry_date": "9.45",
    "supplier": "https://shopee.co.th/product/47780077/29522973196"
  },
  {
    "id": 18489128369,
    "product_name": "Ginno กินโนะ อาหารเปียกแมว เกรดพรีเมี่ยม 60g ปลีก/ซอง",
    "tags": [
      "อาหารแมว",
      "อาหารแมว-เกรดพรีเมียม"
    ],
    "order": 537,
    "price": 17,
    "url_img": "https://down-ws-th.img.susercontent.com/th-11134207-7rasa-m6l2ut8ve71r42.webp",
    "url_shopee": "https://s.shopee.co.th/8fGXH4l3og",
    "location": "Petto Land",
    "sale_date": "7",
    "expiry_date": "1.19",
    "supplier": "https://shopee.co.th/product/76612376/18489128369"
  },
  {
    "id": 24869348850,
    "product_name": "Pawdy อาหารแมวเกรดพรีเมียม Holistic สำหรับแมวโต อายุ 1-6 ปี สูตรทูน่าผสมเนื้อจระเข้ ขนาด 6 กก.",
    "tags": [
      "อาหารแมว",
      "อาหารแมว-เกรดพรีเมียม"
    ],
    "order": 6200,
    "price": 1200,
    "url_img": "https://down-ws-th.img.susercontent.com/th-11134207-7r98p-lsxoc1d2hcql59.webp",
    "url_shopee": "https://s.shopee.co.th/8pZxTNkQTj",
    "location": "Pawdy official",
    "sale_date": "15",
    "expiry_date": "178.50",
    "supplier": "https://shopee.co.th/product/662606594/24869348850"
  },
  {
    "id": 27653331469,
    "product_name": "TUBI อาหารเปียกหน้าแมว อาหารเปียกแมว เกรดพรีเมียม หลากหลายรสชาติ ออล บาลานซ์ 5 ดาว เฟรช",
    "tags": [
      "อาหารแมว",
      "อาหารแมว-เกรดพรีเมียม"
    ],
    "order": 4100,
    "price": 4,
    "url_img": "https://down-ws-th.img.susercontent.com/th-11134207-7r991-lwr222nd93g0c9.webp",
    "url_shopee": "https://s.shopee.co.th/8KdgsSmKUe",
    "location": "TUBI Pet record ",
    "sale_date": "12",
    "expiry_date": "0.48",
    "supplier": "https://shopee.co.th/product/1241023619/27653331469"
  },
  {
    "id": 24619297278,
    "product_name": "Pawdy อาหารแมวเกรดพรีเมียม Holistic สำหรับแมวโต อายุ 1-6 ปี สูตรทูน่าผสมเนื้อจระเข้ ขนาด 1 กก.",
    "tags": [
      "อาหารแมว",
      "อาหารแมว-เกรดพรีเมียม"
    ],
    "order": 1100,
    "price": 265,
    "url_img": "https://down-ws-th.img.susercontent.com/th-11134207-7r98x-lswyfxqp2jlpcc.webp",
    "url_shopee": "https://s.shopee.co.th/8Ux74llh9h",
    "location": "Pawdy official",
    "sale_date": "15",
    "expiry_date": "39.75",
    "supplier": "https://shopee.co.th/product/662606594/24619297278"
  },
  {
    "id": 24770494498,
    "product_name": "(10 กระป๋อง) อาหารแมวเกรดพรีเมี่ยม อาหารแมวเปียก อาหารแมวกระป๋อง อาหารสุนัข 90g.วันที่ผลิตสด พร้อมส่ง",
    "tags": [
      "อาหารแมว",
      "อาหารแมว-เกรดพรีเมียม"
    ],
    "order": 4300,
    "price": 99,
    "url_img": "https://down-ws-th.img.susercontent.com/th-11134207-7r98x-lt7hvbbjj265fe.webp",
    "url_shopee": "https://s.shopee.co.th/800qTqnbAc",
    "location": "PET-HOMIE",
    "sale_date": "4",
    "expiry_date": "3.96",
    "supplier": "https://shopee.co.th/product/378764485/24770494498"
  },
  {
    "id": 24269882930,
    "product_name": "(24 กระป๋อง) Tuna to mee  อาหารแมวเปียก ทูน่าเนื้อขาวในเยลลี่ ทูน่าในน้ำเกรวี่ อาหารแมวเกรดพรีเมี่ยม ขนาด 80 กรัม",
    "tags": [
      "อาหารแมว",
      "อาหารแมว-เกรดพรีเมียม"
    ],
    "order": 1100,
    "price": 300,
    "url_img": "https://down-ws-th.img.susercontent.com/th-11134207-7r98y-ltpd6xfw6m2w72.webp",
    "url_shopee": "https://s.shopee.co.th/8AKGg9mxpf",
    "location": "PIYA Official",
    "sale_date": "7",
    "expiry_date": "21.00",
    "supplier": "https://shopee.co.th/product/37866251/24269882930"
  },
  {
    "id": 29602199707,
    "product_name": "SmartHeart Gold อาหารแมว สมาร์ทฮาร์ท โกลด์ เกรดพรีเมี่ยม ขนาด 1 kg.",
    "tags": [
      "อาหารแมว",
      "อาหารแมว-เกรดพรีเมียม"
    ],
    "order": 2200,
    "price": 199,
    "url_img": "https://down-ws-th.img.susercontent.com/th-11134207-7r98o-lwah60k7d2a7cb.webp",
    "url_shopee": "https://s.shopee.co.th/2Vftvk8XKa",
    "location": "FEED N' FARM",
    "sale_date": "7",
    "expiry_date": "13.93",
    "supplier": "https://shopee.co.th/product/178495558/29602199707"
  },
  {
    "id": 22979575381,
    "product_name": "Pawdy อาหารแมวเกรดพรีเมียม Holistic สำหรับแมวโต อายุ 1-6 ปี สูตรเนื้อแกะและทูน่าผสมเนื้อกุ้ง ขนาด 1 กก.",
    "tags": [
      "อาหารแมว",
      "อาหารแมว-เกรดพรีเมียม"
    ],
    "order": 945,
    "price": 305,
    "url_img": "https://down-ws-th.img.susercontent.com/th-11134207-7r98o-lsxnxg4p4vctcb.webp",
    "url_shopee": "https://s.shopee.co.th/2LMTjR9AfZ",
    "location": "Pawdy official",
    "sale_date": "15",
    "expiry_date": "45.75",
    "supplier": "https://shopee.co.th/product/662606594/22979575381"
  },
  {
    "id": 18652417040,
    "product_name": "[LLP] ( ซื้อ 1แถม1 )Moochie Meaty มูชี่ อาหารเปียกแมว เกรดพรีเมี่ยม ขนาด 70 กรัม(หมดอายุ06/25)",
    "tags": [
      "อาหารแมว",
      "อาหารแมว-เกรดพรีเมียม"
    ],
    "order": 4900,
    "price": 280,
    "url_img": "https://down-ws-th.img.susercontent.com/sg-11134201-22100-xxdcdj5u5bivd7.webp",
    "url_shopee": "https://s.shopee.co.th/2B33X89o0Y",
    "location": "Lovely Petsshop",
    "sale_date": "4",
    "expiry_date": "11.20",
    "supplier": "https://shopee.co.th/product/272100050/18652417040"
  },
  {
    "id": 41900744611,
    "product_name": "อาหารแมว สมาร์ทฮาร์ท โกลด์ SmartHeart Gold  เกรดพรีเมี่ยม 1 กก.(แพคบริษัท 1kg)",
    "tags": [
      "อาหารแมว",
      "อาหารแมว-เกรดพรีเมียม"
    ],
    "order": 10100,
    "price": 185,
    "url_img": "https://down-ws-th.img.susercontent.com/th-11134207-7rasa-m9psmlt07w8h77.webp",
    "url_shopee": "https://s.shopee.co.th/20jdKpARLX",
    "location": "Lanna Petshop",
    "sale_date": "8",
    "expiry_date": "14.80",
    "supplier": "https://shopee.co.th/product/211279961/41900744611"
  },
  {
    "id": 15895712795,
    "product_name": "((ยกกล่อง/ยกเซ็ท-6แพ็ค)) CIAO Sugoi Crunchy อาหารเม็ดแมว เกรดพรีเมี่ยม สูตรเสริมพรีไบโอติก (Prebiotics)",
    "tags": [
      "อาหารแมว",
      "อาหารแมว-เกรดพรีเมียม"
    ],
    "order": 2600,
    "price": 269,
    "url_img": "https://down-ws-th.img.susercontent.com/sg-11134201-7rdyp-lzhjjghqe25e26.webp",
    "url_shopee": "https://s.shopee.co.th/1qQD8WB4gW",
    "location": "Chau Pet World (ชาวเพ็ทเวิร์ล)",
    "sale_date": "4",
    "expiry_date": "10.76",
    "supplier": "https://shopee.co.th/product/799333204/15895712795"
  },
  {
    "id": 20059595930,
    "product_name": "Boom Gold บูมโกลด์อาหารแมว เกรดพรีเมียม ลูกแมว แมวโต โปรตีนจากเนื้อแท้ ขนสวย 1 KG.",
    "tags": [
      "อาหารแมว",
      "อาหารแมว-เกรดพรีเมียม"
    ],
    "order": 3300,
    "price": 119,
    "url_img": "https://down-ws-th.img.susercontent.com/sg-11134201-22110-qjluudvpqejv6b.webp",
    "url_shopee": "https://s.shopee.co.th/1g6mwDBi1V",
    "location": "Petpal-shop",
    "sale_date": "7",
    "expiry_date": "8.33",
    "supplier": "https://shopee.co.th/product/866995884/20059595930"
  },
  {
    "id": 20384629111,
    "product_name": "อาหารเปียกหน้าแมว 85gเกรดพรีเมียม Five-star  complete & balance ทานเป็นมื้อหลักได้",
    "tags": [
      "อาหารแมว",
      "อาหารแมว-เกรดพรีเมียม"
    ],
    "order": 9500,
    "price": 10,
    "url_img": "https://down-ws-th.img.susercontent.com/th-11134207-7r98y-lzj3xak9c5uxf8.webp",
    "url_shopee": "https://s.shopee.co.th/1VnMjuCLMU",
    "location": "Shankk Shop",
    "sale_date": "4",
    "expiry_date": "0.40",
    "supplier": "https://shopee.co.th/product/324564813/20384629111"
  },
  {
    "id": 20881470386,
    "product_name": "((แพ็คใหญ่-1.14Kg.))CIAO Sugoi Crunchy อาหารเม็ดน้องเหมียวเกรดพรีเมี่ยม สูตรเสริมพรีไบโอติก",
    "tags": [
      "อาหารแมว",
      "อาหารแมว-เกรดพรีเมียม"
    ],
    "order": 1100,
    "price": 329,
    "url_img": "https://down-ws-th.img.susercontent.com/sg-11134201-7rdw8-lzhk87qc7j3627.webp",
    "url_shopee": "https://s.shopee.co.th/1LTwXbCyhT",
    "location": "Chau Pet World (ชาวเพ็ทเวิร์ล)",
    "sale_date": "4",
    "expiry_date": "13.16",
    "supplier": "https://shopee.co.th/product/799333204/20881470386"
  },
  {
    "id": 22628621969,
    "product_name": "Ciao Premium Cat Food อาหารแมวเกรดพรีเมี่ยม เกรดเดียวกับที่คนบริโภค ขนาดกระป๋องละ 75g.",
    "tags": [
      "อาหารแมว",
      "อาหารแมว-เกรดพรีเมียม"
    ],
    "order": 733,
    "price": 34,
    "url_img": "https://down-ws-th.img.susercontent.com/sg-11134201-7rd5w-lx6wj73vvgquc9.webp",
    "url_shopee": "https://s.shopee.co.th/1BAWLIDc2S",
    "location": "Chau Pet World (ชาวเพ็ทเวิร์ล)",
    "sale_date": "4",
    "expiry_date": "1.36",
    "supplier": "https://shopee.co.th/product/799333204/22628621969"
  },
  {
    "id": 3748498213,
    "product_name": "[1KG]Buzz Netura อาหารแมวพรีเมียม เกรด Holistic Grain-Free (โฮลิสติก-เกรนฟรี) รวมทุกสูตร ขนาด 1 KG.",
    "tags": [
      "อาหารแมว",
      "อาหารแมว-เกรดพรีเมียม"
    ],
    "order": 160,
    "price": 119,
    "url_img": "https://down-ws-th.img.susercontent.com/th-11134207-7r98z-lzacapjwx7s9f8.webp",
    "url_shopee": "https://s.shopee.co.th/10r68zEFNR",
    "location": "Lanna Petshop",
    "sale_date": "8",
    "expiry_date": "9.52",
    "supplier": "https://shopee.co.th/product/211279961/3748498213"
  },
  {
    "id": 23571836580,
    "product_name": "Buzz Beyond Cat อาหารแมวบัซซ์เกรดพรีเมี่ยม กลูเตนฟรี ขนาด 1kg.",
    "tags": [
      "อาหารแมว",
      "อาหารแมว-เกรดพรีเมียม"
    ],
    "order": 760,
    "price": 125,
    "url_img": "https://down-ws-th.img.susercontent.com/th-11134207-7r98u-lzlvfv3rn24hc1.webp",
    "url_shopee": "https://s.shopee.co.th/qXfwgEsiQ",
    "location": "PET VELAA",
    "sale_date": "4",
    "expiry_date": "5.00",
    "supplier": "https://shopee.co.th/product/831512945/23571836580"
  },
  {
    "id": 28679619868,
    "product_name": "Pawdy อาหารแมวเกรดพรีเมียม Holistic สำหรับแมวโต สูตรสำหรับแมวเลี้ยงในบ้าน รสทูน่าผสมเนื้อจระเข้  6 kg หมดอายุ 22-08-25",
    "tags": [
      "อาหารแมว",
      "อาหารแมว-เกรดพรีเมียม"
    ],
    "order": 35,
    "price": 1200,
    "url_img": "https://down-ws-th.img.susercontent.com/th-11134207-7rasi-m9qq3u38soy780.webp",
    "url_shopee": "https://s.shopee.co.th/gEFkNFW3P",
    "location": "PetPaw ",
    "sale_date": "7",
    "expiry_date": "83.30",
    "supplier": "https://shopee.co.th/product/542831704/28679619868"
  },
  {
    "id": 7692067009,
    "product_name": "Regalos รีกาลอส อาหารแมวเปียกแมว เกรดพรีเมี่ยม เนื้อปลาเน้นๆ ขนาด 70ก.",
    "tags": [
      "อาหารแมว",
      "อาหารแมว-เกรดพรีเมียม"
    ],
    "order": 208,
    "price": 15,
    "url_img": "https://down-ws-th.img.susercontent.com/304f9b87e0a62058ac009f192a5ce5b9.webp",
    "url_shopee": "https://s.shopee.co.th/VupY4G9OO",
    "location": "Sangtongpetmart",
    "sale_date": "4",
    "expiry_date": "0.60",
    "supplier": "https://shopee.co.th/product/141949267/7692067009"
  },
  {
    "id": 1338787185,
    "product_name": "Maria (70g) อาหารแมวเปียกเกรด พรีเมี่ยม รสชาติใหม่มาแล้ว",
    "tags": [
      "อาหารแมว",
      "อาหารแมว-เกรดพรีเมียม"
    ],
    "order": 15700,
    "price": 18,
    "url_img": "https://down-ws-th.img.susercontent.com/291841b9e798367359a58e376774f956.webp",
    "url_shopee": "https://s.shopee.co.th/LbPLlGmjN",
    "location": "Monday Petshop",
    "sale_date": "4",
    "expiry_date": "0.72",
    "supplier": "https://shopee.co.th/product/23178489/1338787185"
  },
  {
    "id": 28822617355,
    "product_name": "คานิมอล ซูพรีโม อาหารแมว  ชนิดเม็ด Kanimal Supremo เกรดพรีเมี่ยม ถุงเล็ก  0.8 กรัม - 1 กิโล  7สูตร",
    "tags": [
      "อาหารแมว",
      "อาหารแมว-เกรดพรีเมียม"
    ],
    "order": 173,
    "price": 128,
    "url_img": "https://down-ws-th.img.susercontent.com/th-11134207-7rasf-m4looge9oeiy1a.webp",
    "url_shopee": "https://s.shopee.co.th/BHz9SHQ4M",
    "location": "VITAMINS SHOP",
    "sale_date": "7",
    "expiry_date": "8.96",
    "supplier": "https://shopee.co.th/product/71303724/28822617355"
  },
  {
    "id": 25192266914,
    "product_name": "[ยกกล่อง]Pramy Carnivore อาหารเปียกแมว พรามี่ คาร์นิวอร์ เกรดพรีเมี่ยม ขนาด 70g. x 12 ซอง",
    "tags": [
      "อาหารแมว",
      "อาหารแมว-เกรดพรีเมียม"
    ],
    "order": 627,
    "price": 183,
    "url_img": "https://down-ws-th.img.susercontent.com/th-11134207-7rask-m6z8ww9uogdc5a.webp",
    "url_shopee": "https://s.shopee.co.th/yYx9I3PL",
    "location": "Lanna Petshop",
    "sale_date": "8",
    "expiry_date": "14.64",
    "supplier": "https://shopee.co.th/product/211279961/25192266914"
  },
  {
    "id": 19659596216,
    "product_name": "Boom Gold บูมโกลด์ อาหารแมว เกรดพรีเมียม ลูกแมว แมวโต โปรตีนจากเนื้อแท้ ขนสวย 7 KG.",
    "tags": [
      "อาหารแมว",
      "อาหารแมว-เกรดพรีเมียม"
    ],
    "order": 503,
    "price": 676,
    "url_img": "https://down-ws-th.img.susercontent.com/sg-11134201-22110-ciwgq3vuqejvd0.webp",
    "url_shopee": "https://s.shopee.co.th/5Agf6dyNvM",
    "location": "Petpal-shop",
    "sale_date": "7",
    "expiry_date": "47.32",
    "supplier": "https://shopee.co.th/product/866995884/19659596216"
  },
  {
    "id": 17880203939,
    "product_name": "Me-o Gold มีโอ โกลด์  อาหารแมว เกรดพรีเมี่ยม อาหารเม็ดแมว มี4สูตรให้เลือก ขนาด  1.2กก.",
    "tags": [
      "อาหารแมว",
      "อาหารแมว-เกรดพรีเมียม"
    ],
    "order": 678,
    "price": 199,
    "url_img": "https://down-ws-th.img.susercontent.com/fc70b8775e20bd0c032c808e219d4394.webp",
    "url_shopee": "https://s.shopee.co.th/50NEuKz1GL",
    "location": "Lovely Petsshop",
    "sale_date": "4",
    "expiry_date": "7.96",
    "supplier": "https://shopee.co.th/product/272100050/17880203939"
  },
  {
    "id": 28570810097,
    "product_name": "อาหารเม็ดแมว และอาหารสุนัข  1.2 Kg. เกรดพรีเมี่ยม บำรุงขน ตัวอ้วนแน่น  มี 3สูตร",
    "tags": [
      "อาหารแมว",
      "อาหารแมว-เกรดพรีเมียม"
    ],
    "order": 106,
    "price": 1,
    "url_img": "https://down-ws-th.img.susercontent.com/th-11134207-7ras8-m3ua3nqur3hjcd.webp",
    "url_shopee": "https://s.shopee.co.th/4q3oi1zebK",
    "location": "DD Cottage",
    "sale_date": "8",
    "expiry_date": "0.08",
    "supplier": "https://shopee.co.th/product/964984243/28570810097"
  },
  {
    "id": 20053583859,
    "product_name": "ผงกุ้งป่น คัดเกรดพรีเมียม จากกุ้งแท้ 100% อาหารหมา อาหารแมว [100 กรัม]",
    "tags": [
      "อาหารแมว",
      "อาหารแมว-เกรดพรีเมียม"
    ],
    "order": 698,
    "price": 49,
    "url_img": "https://down-ws-th.img.susercontent.com/9a958b9e783bd095bd15b85933252db6.webp",
    "url_shopee": "https://s.shopee.co.th/4fkOVj0HwJ",
    "location": "Pet Deli",
    "sale_date": "4",
    "expiry_date": "1.96",
    "supplier": "https://shopee.co.th/product/654895650/20053583859"
  },
  {
    "id": 27105324970,
    "product_name": "Buzz Beyond บัซซ์ บียอนด์ อาหารแมวเกรดพรีเมียม กลูเตนฟรี 1kg",
    "tags": [
      "อาหารแมว",
      "อาหารแมว-เกรดพรีเมียม"
    ],
    "order": 101,
    "price": 119,
    "url_img": "https://down-ws-th.img.susercontent.com/th-11134207-7r98o-lxqnqj18c5gw95.webp",
    "url_shopee": "https://s.shopee.co.th/4VQyJQ0vHI",
    "location": "Petto Land",
    "sale_date": "7",
    "expiry_date": "8.33",
    "supplier": "https://shopee.co.th/product/76612376/27105324970"
  },
  {
    "id": 24183135536,
    "product_name": "อาหารแมวแบบเปียก เกรดพรีเมี่ยม อาหารเปียกแมว อาหารแมวเปียก แบบซอง หลากหลายรสชาติ เกรดซุปเปอร์พรีเมี่ยม 85 กรัม/ชิ้น",
    "tags": [
      "อาหารแมว",
      "อาหารแมว-เกรดพรีเมียม"
    ],
    "order": 57,
    "price": 11,
    "url_img": "https://down-ws-th.img.susercontent.com/sg-11134201-7rdw6-m0l2xlro2vzud1.webp",
    "url_shopee": "https://s.shopee.co.th/4L7Y771YcH",
    "location": "PET Star1",
    "sale_date": "13",
    "expiry_date": "1.43",
    "supplier": "https://shopee.co.th/product/1292554813/24183135536"
  },
  {
    "id": 23128616231,
    "product_name": "((ยกลัง-24 กระป๋อง))CIAO Premium Cat Food อาหารแมวเกรดฟรีเมี่ยม เกรดเดียวกับที่คนบริโภค ขนาดกระป๋องละ75g.",
    "tags": [
      "อาหารแมว",
      "อาหารแมว-เกรดพรีเมียม"
    ],
    "order": 644,
    "price": 840,
    "url_img": "https://down-ws-th.img.susercontent.com/sg-11134201-7rd5n-lx6x0sr2kns609.webp",
    "url_shopee": "https://s.shopee.co.th/4Ao7uo2BxG",
    "location": "Chau Pet World (ชาวเพ็ทเวิร์ล)",
    "sale_date": "4",
    "expiry_date": "33.60",
    "supplier": "https://shopee.co.th/product/799333204/23128616231"
  },
  {
    "id": 24858293903,
    "product_name": "KAT CHEER อาหารแมวเกรดพรีเมี่ยม สูตรแมวเลี้ยงในบ้าน Indoor คลายความเครียด ขนาด 1.3 Kg และ 380 g",
    "tags": [
      "อาหารแมว",
      "อาหารแมว-เกรดพรีเมียม"
    ],
    "order": 1100,
    "price": 79,
    "url_img": "https://down-ws-th.img.susercontent.com/th-11134207-7r990-lr5ps39k9399aa.webp",
    "url_shopee": "https://s.shopee.co.th/40UhiV2pIF",
    "location": "KATCHEER_Siampethouse",
    "sale_date": "10",
    "expiry_date": "7.90",
    "supplier": "https://shopee.co.th/product/1143265511/24858293903"
  },
  {
    "id": 24822434715,
    "product_name": "(1 ลัง 24 กระป๋อง) อาหารแมวเปียกเกรดพรีเมี่ยม อาหารแมวทูน่าขาวในเยลลี่ ขนาด 80 กรัม",
    "tags": [
      "อาหารแมว",
      "อาหารแมว-เกรดพรีเมียม"
    ],
    "order": 105,
    "price": 459,
    "url_img": "https://down-ws-th.img.susercontent.com/th-11134207-7r98o-ltp58kne0ax47c.webp",
    "url_shopee": "https://s.shopee.co.th/3qBHWC3SdE",
    "location": "PIYA Official",
    "sale_date": "7",
    "expiry_date": "32.13",
    "supplier": "https://shopee.co.th/product/37866251/24822434715"
  },
  {
    "id": 27466967535,
    "product_name": "อาหารแมว อาหารเม็ด เกรดพรีเมี่ยม สำหรับแมวทุกช่วงวัย ขนาด 1.5Kg",
    "tags": [
      "อาหารแมว",
      "อาหารแมว-เกรดพรีเมียม"
    ],
    "order": 74,
    "price": 120,
    "url_img": "https://down-ws-th.img.susercontent.com/th-11134207-7rasf-m2gdvuznrdt0b2.webp",
    "url_shopee": "https://s.shopee.co.th/3frrJt45yD",
    "location": "PP shop office",
    "sale_date": "7.20",
    "expiry_date": "8.64",
    "supplier": "https://shopee.co.th/product/1125746922/27466967535"
  },
  {
    "id": 9201208493,
    "product_name": "Monchou มองชู อาหารเปียกแมว เกรดพรีเมี่ยม ขนาด 70ก.",
    "tags": [
      "อาหารแมว",
      "อาหารแมว-เกรดพรีเมียม"
    ],
    "order": 34,
    "price": 19,
    "url_img": "https://down-ws-th.img.susercontent.com/920959f72aee5a6b607c2f37a781f3f7.webp",
    "url_shopee": "https://s.shopee.co.th/3VYR7a4jJC",
    "location": "Sangtongpetmart",
    "sale_date": "4",
    "expiry_date": "0.76",
    "supplier": "https://shopee.co.th/product/141949267/9201208493"
  },
  {
    "id": 41451125216,
    "product_name": "Upaw าหารแมวเกรดพรีเมี่ยม อาหารเม็ดแมว เกรดกลูเตนฟรี โปรตีนสูง58%",
    "tags": [
      "อาหารแมว",
      "อาหารแมว-เกรดพรีเมียม"
    ],
    "order": 8,
    "price": 179,
    "url_img": "https://down-ws-th.img.susercontent.com/th-11134207-7rask-m9tx7pwo4esu96.webp",
    "url_shopee": "https://s.shopee.co.th/3LF0vH5MeB",
    "location": "Upaw Pet Food Shop",
    "sale_date": "11",
    "expiry_date": "19.69",
    "supplier": "https://shopee.co.th/product/421914116/41451125216"
  },
  {
    "id": 9993742884,
    "product_name": "รีกาลอส(Regalos) อาหารเปียกแมว เกรดพรีเมี่ยม70g.",
    "tags": [
      "อาหารแมว",
      "อาหารแมว-เกรดพรีเมียม"
    ],
    "order": 792,
    "price": 15,
    "url_img": "https://down-ws-th.img.susercontent.com/0c309233f6900159b0a8a9f6cac9d13e.webp",
    "url_shopee": "https://s.shopee.co.th/3Avaiy5zzA",
    "location": "krabipetshop",
    "sale_date": "7",
    "expiry_date": "1.05",
    "supplier": "https://shopee.co.th/product/356982566/9993742884"
  },
  {
    "id": 40402435856,
    "product_name": "1 โหลแถม 2 โหล Petsimo อาหารเปียกเกรดพรีเมี่ยมสำหรับแมว ชนิดซอง 70g. แถมรสชาติเดียวกัน",
    "tags": [
      "อาหารแมว",
      "อาหารแมว-เกรดพรีเมียม"
    ],
    "order": 7,
    "price": 312,
    "url_img": "https://down-ws-th.img.susercontent.com/th-11134207-7rase-mab5pbpufpre7b.webp",
    "url_shopee": "https://s.shopee.co.th/30cAWf6dK9",
    "location": "VET PLANET",
    "sale_date": "8",
    "expiry_date": "24.96",
    "supplier": "https://shopee.co.th/product/1478662402/40402435856"
  },
  {
    "id": 19414662225,
    "product_name": "อาหารแมว okiko อาหารเปียกสำหรับแมว สูตร ทูน่าเนื้อขาว ขนาด 70 กรัม ไม่เติมเกลือ เกรดซุปเปอร์พรีเมี่ยม",
    "tags": [
      "อาหารแมว",
      "อาหารแมว-เกรดพรีเมียม"
    ],
    "order": 66,
    "price": 18,
    "url_img": "https://down-ws-th.img.susercontent.com/th-11134207-7r98x-lqyjfuqdzvste7.webp",
    "url_shopee": "https://s.shopee.co.th/2qIkKM7Gf8",
    "location": "Lykcmm",
    "sale_date": "4",
    "expiry_date": "0.72",
    "supplier": "https://shopee.co.th/product/8169199/19414662225"
  },
  {
    "id": 21793444211,
    "product_name": "เคลลี่แอนด์โค รอว์บูส อาหารเม็ด แมว เกรดพรีเมี่ยมผสมฟรีซดราย โปรตีนสูง ปราศจากธัญพืช 1.59 กก.",
    "tags": [
      "อาหารแมว",
      "อาหารแมว-เกรดพรีเมียม"
    ],
    "order": 13,
    "price": 559,
    "url_img": "https://down-ws-th.img.susercontent.com/th-11134207-7r98r-lmr677kgw8em01.webp",
    "url_shopee": "https://s.shopee.co.th/2fzK837u07",
    "location": "kellyandcos",
    "sale_date": "4",
    "expiry_date": "22.36",
    "supplier": "https://shopee.co.th/product/125437207/21793444211"
  },
  {
    "id": 16197993707,
    "product_name": "(ถุงซิป)NEEZ+  Premium Cat Food ❤️😸 นีซพลัส อาหารเม็ดสำหรับแมวเกรดพรีเมี่ยม (ถุงบรรจุ 1kg.)",
    "tags": [
      "อาหารแมว",
      "อาหารแมว-เกรดพรีเมียม"
    ],
    "order": 663,
    "price": 159,
    "url_img": "https://down-ws-th.img.susercontent.com/th-11134207-7qul1-lir52w8l1n8o51.webp",
    "url_shopee": "https://s.shopee.co.th/7phQHXoEW8",
    "location": "OK PetShop",
    "sale_date": "4",
    "expiry_date": "6.36",
    "supplier": "https://shopee.co.th/product/137088280/16197993707"
  },
  {
    "id": 23381256998,
    "product_name": "เคลลี่แอนด์โค รอว์มิกซ์ อาหารเม็ด แมว เกรดพรีเมี่ยมผสมฟรีซดราย โปรตีนสูง ปราศจากธัญพืช 1.59 กก.",
    "tags": [
      "อาหารแมว",
      "อาหารแมว-เกรดพรีเมียม"
    ],
    "order": 15,
    "price": 559,
    "url_img": "https://down-ws-th.img.susercontent.com/th-11134207-7r991-lmr677kgutu67f.webp",
    "url_shopee": "https://s.shopee.co.th/7fO05Eorr7",
    "location": "kellyandcos",
    "sale_date": "4",
    "expiry_date": "22.36",
    "supplier": "https://shopee.co.th/product/125437207/23381256998"
  },
  {
    "id": 27656059493,
    "product_name": "Pramy Carnivore อาหารเปียกแมว เกรดพรีเมี่ยม ขนาด 70g (ยกกล่อง 12 ซอง)",
    "tags": [
      "อาหารแมว",
      "อาหารแมว-เกรดพรีเมียม"
    ],
    "order": 15,
    "price": 84,
    "url_img": "https://down-ws-th.img.susercontent.com/th-11134207-7rase-m1mu1i405ppl32.webp",
    "url_shopee": "https://s.shopee.co.th/7V4ZsvpVC6",
    "location": "tanapetshop",
    "sale_date": "8",
    "expiry_date": "6.72",
    "supplier": "https://shopee.co.th/product/153279689/27656059493"
  },
  {
    "id": 11133667158,
    "product_name": "🐶🌸Pet4You🌸🐱(กล่อง*12ซอง) Me-O delight มีโอแมว อาหารเปียก  มีโอ ดีไลท์ อาหารแมว ชนิดซอง 70 กรัม อาหารแมวเกรดพรีเมี่ยม",
    "tags": [
      "อาหารแมว",
      "อาหารแมว-เกรดพรีเมียม"
    ],
    "order": 13,
    "price": 222,
    "url_img": "https://down-ws-th.img.susercontent.com/e11625b4d013be732ee4a6f01fa13a84.webp",
    "url_shopee": "https://s.shopee.co.th/7Kl9gcq8X5",
    "location": "pet4you",
    "sale_date": "7",
    "expiry_date": "15.54",
    "supplier": "https://shopee.co.th/product/54877452/11133667158"
  },
  {
    "id": 27067243573,
    "product_name": "อาหารแมว อาหารเม็ด เกรดพรีเมี่ยม สำหรับแมวทุกช่วงวัย ขนาด  แคทคลับ เม็ดเล็ก ราคาถูก อาหารแมว 1.5Kg",
    "tags": [
      "อาหารแมว",
      "อาหารแมว-เกรดพรีเมียม"
    ],
    "order": 25,
    "price": 120,
    "url_img": "https://down-ws-th.img.susercontent.com/th-11134207-7rasf-m2geokqkzun5da.webp",
    "url_shopee": "https://s.shopee.co.th/7ARjUJqls4",
    "location": "PP shop office",
    "sale_date": "7.20",
    "expiry_date": "8.64",
    "supplier": "https://shopee.co.th/product/1125746922/27067243573"
  },
  {
    "id": 27313411734,
    "product_name": "Monge Lechat อาหารเปียกแมวเกรดพรีเมี่ยมจากอิตาลี  รสทูน่าและแซลมอนชิ้นแน่นเต็มซอง (100g)",
    "tags": [
      "อาหารแมว",
      "อาหารแมว-เกรดพรีเมียม"
    ],
    "order": 2,
    "price": 29,
    "url_img": "https://down-ws-th.img.susercontent.com/th-11134207-7rasm-m12hw1n46lbt79.webp",
    "url_shopee": "https://s.shopee.co.th/708JI0rPD3",
    "location": "TailyBuddy Pet Shop Online",
    "sale_date": "10",
    "expiry_date": "2.90",
    "supplier": "https://shopee.co.th/product/182647826/27313411734"
  },
  {
    "id": 24255088602,
    "product_name": "Me-o Gold อาหารแมว มีโอโกลด์ แบบเม็ด ขนาด 2.8 kg มี 4 สูตรให้เลือก เกรดพรีเมี่ยม อาหารแมวโต แมวเลี้ยงในบ้าน เปอร์เซีย",
    "tags": [
      "อาหารแมว",
      "อาหารแมว-เกรดพรีเมียม"
    ],
    "order": 0,
    "price": 449,
    "url_img": "https://down-ws-th.img.susercontent.com/sg-11134201-7rbk9-lpq92rh0w7kz5d.webp",
    "url_shopee": "https://s.shopee.co.th/6pot5hs2Y2",
    "location": "THUNDER RACING THAILAND",
    "sale_date": "7",
    "expiry_date": "31.43",
    "supplier": "https://shopee.co.th/product/2684876/24255088602"
  },
  {
    "id": 1455481010,
    "product_name": "[1 kg.] Maxima CAT แม็คซิม่า อาหารเม็ดแมว เกรดพรีเมี่ยม สูตรเนื้อแกะ  - ไซส์แบ่งขาย ขนาด 1 kg",
    "tags": [
      "อาหารแมว",
      "อาหารแมว-เกรดพรีเมียม"
    ],
    "order": 146,
    "price": 75,
    "url_img": "https://down-ws-th.img.susercontent.com/sg-11134201-7rdyn-lxdtf5m4iqh6f9.webp",
    "url_shopee": "https://s.shopee.co.th/6fVStOsft1",
    "location": "Pet Choka",
    "sale_date": "4",
    "expiry_date": "3.00",
    "supplier": "https://shopee.co.th/product/77730360/1455481010"
  },
  {
    "id": 40902436205,
    "product_name": "1 โหลแถม 1 โหล Petsimo อาหารเปียกเกรดพรีเมี่ยมสำหรับแมว กระป๋อง 85g. แถมรสชาติเดียวกัน",
    "tags": [
      "อาหารแมว",
      "อาหารแมว-เกรดพรีเมียม"
    ],
    "order": 1,
    "price": 420,
    "url_img": "https://down-ws-th.img.susercontent.com/th-11134207-7rasl-mab67ra5cpzn54.webp",
    "url_shopee": "https://s.shopee.co.th/6VC2h5tJE0",
    "location": "VET PLANET",
    "sale_date": "8",
    "expiry_date": "33.60",
    "supplier": "https://shopee.co.th/product/1478662402/40902436205"
  },
  {
    "id": 26329041574,
    "product_name": "Pramy Carnivore อาหารเปียกแมว เกรดพรีเมี่ยม กลูเตนฟรี ขนาด 70 กรัมต่อซอง",
    "tags": [
      "อาหารแมว",
      "อาหารแมว-เกรดพรีเมียม"
    ],
    "order": 0,
    "price": 22,
    "url_img": "https://down-ws-th.img.susercontent.com/th-11134207-7rasm-m767yv75kzhxc8.webp",
    "url_shopee": "https://s.shopee.co.th/6KscUmtwYz",
    "location": "NY Pet Haven",
    "sale_date": "8",
    "expiry_date": "1.76",
    "supplier": "https://shopee.co.th/product/1491387769/26329041574"
  },
  {
    "id": 27060429325,
    "product_name": "Nekko gold(12ซอง) อาหารเปียกแมวแบบซอง เกรดพรีเมี่ยม มี 7 รสชาตขนาด 70 กรัม",
    "tags": [
      "อาหารแมว",
      "อาหารแมว-เกรดพรีเมียม"
    ],
    "order": 15,
    "price": 235,
    "url_img": "https://down-ws-th.img.susercontent.com/th-11134207-7r98o-lzuits3iukjl56.webp",
    "url_shopee": "https://s.shopee.co.th/6AZCITuZty",
    "location": "The house pet shop",
    "sale_date": "7",
    "expiry_date": "16.45",
    "supplier": "https://shopee.co.th/product/567964861/27060429325"
  },
  {
    "id": 29229010742,
    "product_name": "[48 ซอง ยกลัง]Pramy Carnivore อาหารเปียกแมว เกรดพรีเมี่ยม กลูเตนฟรี ขนาด 70 กรัมต่อซอง",
    "tags": [
      "อาหารแมว",
      "อาหารแมว-เกรดพรีเมียม"
    ],
    "order": 0,
    "price": 759,
    "url_img": "https://down-ws-th.img.susercontent.com/th-11134207-7rase-m75yy69wwoxb01.webp",
    "url_shopee": "https://s.shopee.co.th/60Fm6AvDEx",
    "location": "NY Pet Haven",
    "sale_date": "8",
    "expiry_date": "60.72",
    "supplier": "https://shopee.co.th/product/1491387769/29229010742"
  },
  {
    "id": 28379040982,
    "product_name": "[12 ซอง ยกกล่อง] Pramy Carnivore อาหารเปียกแมว เกรดพรีเมี่ยม กลูเตนฟรี ขนาด 70 กรัมต่อซอง",
    "tags": [
      "อาหารแมว",
      "อาหารแมว-เกรดพรีเมียม"
    ],
    "order": 0,
    "price": 189,
    "url_img": "https://down-ws-th.img.susercontent.com/th-11134207-7rask-m767eh23y59r60.webp",
    "url_shopee": "https://s.shopee.co.th/5pwLtrvqZw",
    "location": "NY Pet Haven",
    "sale_date": "8",
    "expiry_date": "15.12",
    "supplier": "https://shopee.co.th/product/1491387769/28379040982"
  },
  {
    "id": 23455760890,
    "product_name": "เคลลี่แอนด์โค เอสเซนเชียล อาหารเม็ด แมว เกรดพรีเมี่ยม โปรตีนสูง ปราศจากธัญพืช 1.59 กก.",
    "tags": [
      "อาหารแมว",
      "อาหารแมว-เกรดพรีเมียม"
    ],
    "order": 36,
    "price": 390,
    "url_img": "https://down-ws-th.img.susercontent.com/th-11134207-7r992-lmr6vbxjzslqa6.webp",
    "url_shopee": "https://s.shopee.co.th/5fcvhYwTuv",
    "location": "kellyandcos",
    "sale_date": "4",
    "expiry_date": "15.60",
    "supplier": "https://shopee.co.th/product/125437207/23455760890"
  }
]