[
  {
    "id": 25023596513,
    "product_name": "FOLOPETS 5L/10L ครอกแมวเบนโทไนท์ เบนโตไนท์ เกรดอาหาร ควบคุมกลิ่น จับเป็นก้อน ดูดซับน้ําได้สูง คละแบบ",
    "tags": [
      "อาหารแมว",
      "อาหารแมว-ยี่ห้อไหนดี-ลดกลิ่น"
    ],
    "order": 2700,
    "price": 68,
    "url_img": "https://down-zl-th.img.susercontent.com/cn-11134207-7ras8-m4e469r0aqefd6.webp",
    "url_shopee": "https://s.shopee.co.th/5fd0ffsZsl",
    "location": "FOLOPETS Official Store",
    "sale_date": "7",
    "expiry_date": "4.76",
    "supplier": "https://shopee.co.th/product/1223233659/25023596513"
  },
  {
    "id": 20980825529,
    "product_name": "(12 ซอง) Kaniva Indoor Pouch อาหารแมวคานิว่า ชนิดเปียก ช่วยควบคุมน้ำหนัก ลดกลิ่นมูล ขนาด 70 กรัม",
    "tags": [
      "อาหารแมว",
      "อาหารแมว-ยี่ห้อไหนดี-ลดกลิ่น"
    ],
    "order": 2000,
    "price": 259,
    "url_img": "https://down-zl-th.img.susercontent.com/th-11134207-7rasc-mai7xwa9xadb91.webp",
    "url_shopee": "https://s.shopee.co.th/AA5Q1wbRke",
    "location": "Pet Protect Thailand",
    "sale_date": "4",
    "expiry_date": "10.36",
    "supplier": "https://shopee.co.th/product/185844020/20980825529"
  },
  {
    "id": 25773596204,
    "product_name": "Folopets กระบะทรายแมว เบนโตไนท์ 5 ลิตร เกรดอาหาร ควบคุมกลิ่น จับเป็นก้อน ดูดซับน้ําได้สูง คละแบบ",
    "tags": [
      "อาหารแมว",
      "อาหารแมว-ยี่ห้อไหนดี-ลดกลิ่น"
    ],
    "order": 138,
    "price": 72,
    "url_img": "https://down-zl-th.img.susercontent.com/cn-11134207-7ras8-m4e536nachdj07.webp",
    "url_shopee": "https://s.shopee.co.th/9zlzpdc55d",
    "location": "FOLOPETS Official Store",
    "sale_date": "7",
    "expiry_date": "5.04",
    "supplier": "https://shopee.co.th/product/1223233659/25773596204"
  },
  {
    "id": 18675367759,
    "product_name": "Kaniva Indoor 2.8 KG. อาหารแมว สูตรเนื้อไก่งวง ปลาแซลมอนและข้าว เน้นควบคุมน้ำหนัก ลดกลิ่นมูลและฉี่ สำหรับแมวเลี้ยงในบ้าน",
    "tags": [
      "อาหารแมว",
      "อาหารแมว-ยี่ห้อไหนดี-ลดกลิ่น"
    ],
    "order": 727,
    "price": 529,
    "url_img": "https://down-zl-th.img.susercontent.com/th-11134207-7rasm-mai89j52zbec8f.webp",
    "url_shopee": "https://s.shopee.co.th/AUiGQYaB4k",
    "location": "Pet Protect Thailand",
    "sale_date": "4",
    "expiry_date": "21.16",
    "supplier": "https://shopee.co.th/product/185844020/18675367759"
  },
  {
    "id": 18877699728,
    "product_name": "(48 ซอง / ลัง) Kaniva Indoor Pouch อาหารแมวคานิว่า ชนิดเปียก ช่วยควบคุมน้ำหนัก ลดกลิ่นมูล ขนาด 70 กรัม",
    "tags": [
      "อาหารแมว",
      "อาหารแมว-ยี่ห้อไหนดี-ลดกลิ่น"
    ],
    "order": 181,
    "price": 1000,
    "url_img": "https://down-zl-th.img.susercontent.com/th-11134207-7rasc-mai7xwa9xadb91.webp",
    "url_shopee": "https://s.shopee.co.th/AKOqEFaoPj",
    "location": "Pet Protect Thailand",
    "sale_date": "4",
    "expiry_date": "41.40",
    "supplier": "https://shopee.co.th/product/185844020/18877699728"
  },
  {
    "id": 18175363868,
    "product_name": "Kaniva Indoor 8 KG. อาหารแมว สูตรเนื้อไก่งวง ปลาแซลมอนและข้าว เน้นควบคุมน้ำหนัก ลดกลิ่นมูลและฉี่ สำหรับแมวเลี้ยงในบ้าน",
    "tags": [
      "อาหารแมว",
      "อาหารแมว-ยี่ห้อไหนดี-ลดกลิ่น"
    ],
    "order": 315,
    "price": 1600,
    "url_img": "https://down-zl-th.img.susercontent.com/th-11134207-7rasd-mai833s5jozabc.webp",
    "url_shopee": "https://s.shopee.co.th/9UpjEidz6a",
    "location": "Pet Protect Thailand",
    "sale_date": "4",
    "expiry_date": "62.00",
    "supplier": "https://shopee.co.th/product/185844020/18175363868"
  },
  {
    "id": 13698483489,
    "product_name": "Kaniva Indoor 1.3 KG. อาหารแมว สูตรเนื้อไก่งวง ปลาแซลมอนและข้าว เน้นควบคุมน้ำหนัก ลดกลิ่นมูลและฉี่ สำหรับแมวเลี้ยงในบ้าน",
    "tags": [
      "อาหารแมว",
      "อาหารแมว-ยี่ห้อไหนดี-ลดกลิ่น"
    ],
    "order": 549,
    "price": 269,
    "url_img": "https://down-zl-th.img.susercontent.com/th-11134207-7rasm-mai89j52zbec8f.webp",
    "url_shopee": "https://s.shopee.co.th/9KWJ2PecRZ",
    "location": "Pet Protect Thailand",
    "sale_date": "4",
    "expiry_date": "10.76",
    "supplier": "https://shopee.co.th/product/185844020/13698483489"
  },
  {
    "id": 28532036784,
    "product_name": "(12 ซอง) Kaniva Indoor Pouch อาหารแมวคานิว่า ชนิดเปียก ช่วยควบคุมน้ำหนัก ลดกลิ่นมูล ขนาด 70 กรัม",
    "tags": [
      "อาหารแมว",
      "อาหารแมว-ยี่ห้อไหนดี-ลดกลิ่น"
    ],
    "order": 7900,
    "price": 215,
    "url_img": "https://down-zl-th.img.susercontent.com/th-11134207-7rasc-m8666x2665vzc5.webp",
    "url_shopee": "https://s.shopee.co.th/9pSZdKciQg",
    "location": "Petus สัตว์เลี้ยง",
    "sale_date": "13",
    "expiry_date": "27.95",
    "supplier": "https://shopee.co.th/product/1438612338/28532036784"
  },
  {
    "id": 17396250451,
    "product_name": "Cat's Taste อาหารเปียกแมว ทูน่าในเยลลี่ สูตรควบคุมกลิ่น (เติมแครนเบอร์รี่) ไม่เติมโซเดียม ขนาด 70 กรัม ยกลัง 48 ซอง",
    "tags": [
      "อาหารแมว",
      "อาหารแมว-ยี่ห้อไหนดี-ลดกลิ่น"
    ],
    "order": 108,
    "price": 779,
    "url_img": "https://down-zl-th.img.susercontent.com/th-11134207-7rasb-mai5b6b4myycdb.webp",
    "url_shopee": "https://s.shopee.co.th/9f99R1dLlf",
    "location": "Cat's Taste Official Store",
    "sale_date": "10",
    "expiry_date": "77.90",
    "supplier": "https://shopee.co.th/product/582216451/17396250451"
  },
  {
    "id": 20175571681,
    "product_name": "Kaniva Indoor 370 G. อาหารแมว สูตรเนื้อไก่งวง ปลาแซลมอนและข้าว เน้นควบคุมน้ำหนัก ลดกลิ่นมูลและฉี่ สำหรับแมวเลี้ยงในบ้าน",
    "tags": [
      "อาหารแมว",
      "อาหารแมว-ยี่ห้อไหนดี-ลดกลิ่น"
    ],
    "order": 236,
    "price": 89,
    "url_img": "https://down-zl-th.img.susercontent.com/th-11134207-7rasm-mai89j52zbec8f.webp",
    "url_shopee": "https://s.shopee.co.th/8pa2RUgWSW",
    "location": "Pet Protect Thailand",
    "sale_date": "4",
    "expiry_date": "3.56",
    "supplier": "https://shopee.co.th/product/185844020/20175571681"
  },
  {
    "id": 18784802600,
    "product_name": "Cat's Taste  อาหารเปียกแมว ทูน่าในเยลลี่ สูตรควบคุมกลิ่น (เติมแครนเบอร์รี่) ไม่เติมโซเดียม ขนาด 70 กรัม x 12 ซอง",
    "tags": [
      "อาหารแมว",
      "อาหารแมว-ยี่ห้อไหนดี-ลดกลิ่น"
    ],
    "order": 338,
    "price": 195,
    "url_img": "https://down-zl-th.img.susercontent.com/th-11134207-7rasm-mai5ipsiq93k5a.webp",
    "url_shopee": "https://s.shopee.co.th/8fGcFBh9nV",
    "location": "Cat's Taste Official Store",
    "sale_date": "10",
    "expiry_date": "19.50",
    "supplier": "https://shopee.co.th/product/582216451/18784802600"
  },
  {
    "id": 40553755376,
    "product_name": "[LIVE ONLY] MR.VET T4 อาหารแมวแบบแห้ง 1กก. แพ็ค สูตรโฮลิสติก ออกแบบมาเป็นพิเศษสําหรับแมวในร่มและการควบคุมกลิ่น",
    "tags": [
      "อาหารแมว",
      "อาหารแมว-ยี่ห้อไหนดี-ลดกลิ่น"
    ],
    "order": 0,
    "price": 209,
    "url_img": "https://down-zl-th.img.susercontent.com/cn-11134207-7ras8-matpm85nk6ntfe.webp",
    "url_shopee": "https://s.shopee.co.th/9ACsq6fFmc",
    "location": "Mr_vet.th",
    "sale_date": "9",
    "expiry_date": "18.81",
    "supplier": "https://shopee.co.th/product/1382303842/40553755376"
  },
  {
    "id": 22650028983,
    "product_name": "Kaniva Indoor Pouch อาหารแมวคานิว่า ชนิดเปียก ช่วยควบคุมน้ำหนัก ลดกลิ่นมูล ขนาด 70 กรัม (48 ซอง / ลัง)",
    "tags": [
      "อาหารแมว",
      "อาหารแมว-ยี่ห้อไหนดี-ลดกลิ่น"
    ],
    "order": 0,
    "price": 1100,
    "url_img": "https://down-zl-th.img.susercontent.com/sg-11134201-7qvei-ljwjw4xfcwc78c.webp",
    "url_shopee": "https://s.shopee.co.th/8ztSdnft7b",
    "location": "PetPal_Shop",
    "sale_date": "7",
    "expiry_date": "73.92",
    "supplier": "https://shopee.co.th/product/1028288776/22650028983"
  },
  {
    "id": 22650015673,
    "product_name": "Kaniva Indoor 1.3 KG. อาหารแมว สูตรเนื้อไก่งวง ปลาแซลมอนและข้าว เน้นควบคุมน้ำหนัก ลดกลิ่นมูลและฉี่ สำหรับแมวเลี้ยงในบ้าน",
    "tags": [
      "อาหารแมว",
      "อาหารแมว-ยี่ห้อไหนดี-ลดกลิ่น"
    ],
    "order": 0,
    "price": 269,
    "url_img": "https://down-zl-th.img.susercontent.com/sg-11134201-7qvfc-ljwe0zgh89jqb6.webp",
    "url_shopee": "https://s.shopee.co.th/8AKLeGj3oS",
    "location": "PetPal_Shop",
    "sale_date": "7",
    "expiry_date": "18.83",
    "supplier": "https://shopee.co.th/product/1028288776/22650015673"
  },
  {
    "id": 21582470487,
    "product_name": "Kaniva Indoor 8 KG. อาหารแมว สูตรเนื้อไก่งวง ปลาแซลมอนและข้าว เน้นควบคุมน้ำหนัก ลดกลิ่นมูลและฉี่ สำหรับแมวเลี้ยงในบ้าน",
    "tags": [
      "อาหารแมว",
      "อาหารแมว-ยี่ห้อไหนดี-ลดกลิ่น"
    ],
    "order": 1,
    "price": 1600,
    "url_img": "https://down-zl-th.img.susercontent.com/sg-11134201-7qvdy-ljwea74vti4q54.webp",
    "url_shopee": "https://s.shopee.co.th/800vRxjh9R",
    "location": "PetPal_Shop",
    "sale_date": "7",
    "expiry_date": "108.50",
    "supplier": "https://shopee.co.th/product/1028288776/21582470487"
  },
  {
    "id": 21382460798,
    "product_name": "Kaniva Indoor 2.8 KG. อาหารแมว สูตรเนื้อไก่งวง ปลาแซลมอนและข้าว เน้นควบคุมน้ำหนัก ลดกลิ่นมูลและฉี่ สำหรับแมวเลี้ยงในบ้าน",
    "tags": [
      "อาหารแมว",
      "อาหารแมว-ยี่ห้อไหนดี-ลดกลิ่น"
    ],
    "order": 0,
    "price": 540,
    "url_img": "https://down-zl-th.img.susercontent.com/sg-11134201-7qvg3-ljvd5zlhiuno5b.webp",
    "url_shopee": "https://s.shopee.co.th/8UxC2shn8Y",
    "location": "PetPal_Shop",
    "sale_date": "7",
    "expiry_date": "37.80",
    "supplier": "https://shopee.co.th/product/1028288776/21382460798"
  },
  {
    "id": 18291426149,
    "product_name": "Kaniva Indoor 370 G. อาหารแมว สูตรเนื้อไก่งวง ปลาแซลมอนและข้าว เน้นควบคุมน้ำหนัก ลดกลิ่นมูลและฉี่ สำหรับแมวเลี้ยงในบ้าน",
    "tags": [
      "อาหารแมว",
      "อาหารแมว-ยี่ห้อไหนดี-ลดกลิ่น"
    ],
    "order": 0,
    "price": 89,
    "url_img": "https://down-zl-th.img.susercontent.com/sg-11134201-7qvfc-ljwjtx0oaopj74.webp",
    "url_shopee": "https://s.shopee.co.th/8KdlqZiQTX",
    "location": "PetPal_Shop",
    "sale_date": "7",
    "expiry_date": "6.23",
    "supplier": "https://shopee.co.th/product/1028288776/18291426149"
  },
  {
    "id": 42503750759,
    "product_name": "[LIVE ONLY] MR.VET T4 อาหารแมวแบบแห้ง 3กก. แพ็ค สูตรโฮลิสติก ออกแบบมาเป็นพิเศษสําหรับแมวในร่มและการควบคุมกลิ่น",
    "tags": [
      "อาหารแมว",
      "อาหารแมว-ยี่ห้อไหนดี-ลดกลิ่น"
    ],
    "order": 0,
    "price": 627,
    "url_img": "https://down-zl-th.img.susercontent.com/cn-11134207-7ras8-matpf2771sud82.webp",
    "url_shopee": "https://s.shopee.co.th/2B38VF5tzM",
    "location": "Mr_vet.th",
    "sale_date": "9",
    "expiry_date": "56.43",
    "supplier": "https://shopee.co.th/product/1382303842/42503750759"
  },
  {
    "id": 41350135345,
    "product_name": "Purina Pro Plan อาหารแมวในร่มสําหรับผู้ใหญ่ Hairball Management Digestive Care โปรไบโอติก Inulin เพิ่มการควบคุมกลิ่นสตูล",
    "tags": [
      "อาหารแมว",
      "อาหารแมว-ยี่ห้อไหนดี-ลดกลิ่น"
    ],
    "order": 0,
    "price": 1700,
    "url_img": "https://down-zl-th.img.susercontent.com/sg-11134201-7rfgf-m9i8w6g4i2f436.webp",
    "url_shopee": "https://s.shopee.co.th/20jiIw6XKL",
    "location": "Molumo",
    "sale_date": "7",
    "expiry_date": "120.26",
    "supplier": "https://shopee.co.th/product/1261468724/41350135345"
  },
  {
    "id": 26705622873,
    "product_name": "[12ซอง] Kaniva Indoor Pouch อาหารแมว ชนิดเปียก ช่วยควบคุมน้ำหนัก ลดกลิ่นมูล",
    "tags": [
      "อาหารแมว",
      "อาหารแมว-ยี่ห้อไหนดี-ลดกลิ่น"
    ],
    "order": 9,
    "price": 236,
    "url_img": "https://down-zl-th.img.susercontent.com/sg-11134201-7rdwm-lxut04miab7w22.webp",
    "url_shopee": "https://s.shopee.co.th/2Vfytr4dJS",
    "location": "kokoni shop",
    "sale_date": "9",
    "expiry_date": "21.24",
    "supplier": "https://shopee.co.th/product/1187139145/26705622873"
  }
]